dingdingrobot/__init__.py
dingdingrobot/dingding_robot.py
dingdingrobot-1.0.4.dist-info/METADATA
dingdingrobot-1.0.4.dist-info/WHEEL
dingdingrobot-1.0.4.dist-info/top_level.txt
dingdingrobot-1.0.4.dist-info/RECORD
