Metadata-Version: 2.1
Name: dingdingrobot
Version: 1.0.4
Summary: send message to dingtalk robot
Home-page: https://github.com/x-hezhang/dingtalk-robot
Author: zhanghe
Author-email: x_hezhang@126.com
License: GNU GPLv3
Keywords: dingding,dingtalk,robot,dingdingrobot,dingtalk-robot,dingtalk-webhook
Platform: UNKNOWN
Requires-Dist: requests
